LICENSE
MANIFEST.in
README
setup.py
confutils/__init__.py
confutils/compat.py
confutils/configfile.py
confutils/configreader.py
confutils/helpers.py
confutils/merged_config.py
confutils.egg-info/PKG-INFO
confutils.egg-info/SOURCES.txt
confutils.egg-info/dependency_links.txt
confutils.egg-info/top_level.txt
doc/Makefile
doc/conf.py
doc/index.rst
doc/make.bat
doc/_static/.keep_dir
tests/__init__.py
tests/compat.py
tests/configfile.py
tests/helpers.py
tests/merged_config.py