Metadata-Version: 1.1
Name: confutils
Version: 0.3.7
Summary: Advanced configuration file utilities.
Home-page: http://github.com/rbarrois/confutils
Author: Raphaël Barrois
Author-email: raphael.barrois+confutils@polytechnique.org
License: BSD
Download-URL: http://pypi.python.org/pypi/confutils/
Keywords: project,library,template
Platform: UNKNOWN
Classifier: Development Status :: 4 - Beta
Classifier: Intended Audience :: Developers
Classifier: License :: OSI Approved :: BSD License
Classifier: Operating System :: OS Independent
Classifier: Programming Language :: Python :: 2.6
Classifier: Programming Language :: Python :: 2.7
Classifier: Programming Language :: Python :: 3
Classifier: Programming Language :: Python
Classifier: Topic :: Software Development :: Libraries :: Python Modules
